<?xml version="1.0" encoding="UTF-8"?>
<objects serializationModel="Studio.02.02.00">
	<object class="ParameterPreset" id="{bd34f9f4-5aaa-4e47-8b83-afbedb275a8c}">
		<property name="name">
			<value>VolumeRats</value>
		</property>
		<relationship name="folder">
			<destination>{5a601433-230e-44e2-b6c1-21c4612efc75}</destination>
		</relationship>
		<relationship name="parameter">
			<destination>{1b0e3377-3623-4285-b897-5f1a74b33eda}</destination>
		</relationship>
	</object>
	<object class="GameParameter" id="{1b0e3377-3623-4285-b897-5f1a74b33eda}">
		<property name="initialValue">
			<value>1</value>
		</property>
	</object>
</objects>
